config/__init__.py
config/setup.py
config/utl_config.py
logger/__init__.py
logger/setup.py
logger/utl_logger.py
emp_config-0.1.0.dist-info/LICENSE.md
emp_config-0.1.0.dist-info/METADATA
emp_config-0.1.0.dist-info/WHEEL
emp_config-0.1.0.dist-info/top_level.txt
emp_config-0.1.0.dist-info/RECORD
