Metadata-Version: 2.1
Name: emp-config
Version: 0.1.0
Summary: Custom configuration loader with integrated Fallback to local retrievement of environment variables in case Spring Config Server isn't available
Home-page: https://github.com/AbdoCherry/EMP_UTL-S
Author: AbdoCherry
License: MIT
Platform: UNKNOWN
Classifier: Programming Language :: Python :: 3
Classifier: License :: OSI Approved :: MIT License
Classifier: Operating System :: OS Independent
License-File: LICENSE.md
Requires-Dist: attrs (==24.2.0)
Requires-Dist: boltons (==24.1.0)
Requires-Dist: certifi (==2024.8.30)
Requires-Dist: charset-normalizer (==3.4.0)
Requires-Dist: config-client (==1.4.0)
Requires-Dist: face (==24.0.0)
Requires-Dist: glom (==24.11.0)
Requires-Dist: idna (==3.10)
Requires-Dist: requests (==2.32.3)
Requires-Dist: urllib3 (==2.2.3)
